discord_message_components/__init__.py
discord_message_components/classes.py
discord_message_components/funcs.py
discord_message_components/utils.py
discord_message_components_polarsbear-0.1.2.dist-info/LICENSE
discord_message_components_polarsbear-0.1.2.dist-info/METADATA
discord_message_components_polarsbear-0.1.2.dist-info/WHEEL
discord_message_components_polarsbear-0.1.2.dist-info/top_level.txt
discord_message_components_polarsbear-0.1.2.dist-info/RECORD
