Metadata-Version: 2.1
Name: discord-message-components-polarsbear
Version: 0.1.2
Summary: A python library that adds message component support to discord bots
Home-page: https://github.com/PolarsBear/Discord-Message-Components
Author: Lars Von Wangenheim
Author-email: larzitovw@gmail.com
Project-URL: Bug Tracker, https://github.com/PolarsBear/Discord-Message-Components/issues
Classifier: Programming Language :: Python :: 3
Classifier: License :: OSI Approved :: MIT License
Classifier: Operating System :: OS Independent
Requires-Python: >=3.6
License-File: LICENSE
Requires-Dist: discord
